cloudsnorkel/cdk_rds_sanitized_snapshots/__init__.py
cloudsnorkel/cdk_rds_sanitized_snapshots/py.typed
cloudsnorkel/cdk_rds_sanitized_snapshots/_jsii/__init__.py
cloudsnorkel/cdk_rds_sanitized_snapshots/_jsii/cdk-rds-sanitized-snapshots@0.1.5.jsii.tgz
cloudsnorkel_cdk_rds_sanitized_snapshots-0.1.5.dist-info/LICENSE
cloudsnorkel_cdk_rds_sanitized_snapshots-0.1.5.dist-info/METADATA
cloudsnorkel_cdk_rds_sanitized_snapshots-0.1.5.dist-info/WHEEL
cloudsnorkel_cdk_rds_sanitized_snapshots-0.1.5.dist-info/top_level.txt
cloudsnorkel_cdk_rds_sanitized_snapshots-0.1.5.dist-info/RECORD
